datakit_project/__init__.py
datakit_project/cookiecutters.py
datakit_project/exceptions.py
datakit_project/prompt.py
datakit_project/repository.py
datakit_project/utils.py
datakit_project/commands/__init__.py
datakit_project/commands/command_helpers.py
datakit_project/commands/create.py
datakit_project/commands/help_text.py
datakit_project/commands/templates.py
datakit_project/commands/templates_update.py
datakit_project/formatters/__init__.py
datakit_project/formatters/templates.py
tests/__init__.py
tests/conftest.py
tests/test_utils.py
tests/commands/test_create.py
tests/commands/test_create_autogen_plugins_dir.py
tests/commands/test_create_interactive.py
tests/commands/test_templates.py
tests/commands/test_templates_status.py
tests/commands/test_templates_update.py
tests/fake-repo/cookiecutter.json
tests/fake-repo/{{cookiecutter.project_slug}}/README.md
tests/fake-repo-two/cookiecutter.json
tests/fake-repo-two/{{cookiecutter.project_slug}}/README.md
datakit_project-0.5.0.dist-info/LICENSE
datakit_project-0.5.0.dist-info/METADATA
datakit_project-0.5.0.dist-info/WHEEL
datakit_project-0.5.0.dist-info/entry_points.txt
datakit_project-0.5.0.dist-info/top_level.txt
datakit_project-0.5.0.dist-info/RECORD
