Metadata-Version: 2.1
Name: datakit-project
Version: 0.5.0
Summary: A datakit plugin to generate new projects.
Home-page: https://datakit.ap.org
Author: Serdar Tumgoren
Author-email: zstumgoren@gmail.com
License: ISCL
Project-URL: Maintainer, https://github.com/associatedpress
Project-URL: Source, https://github.com/associatedpress/datakit-project
Project-URL: Tracker, https://github.com/associatedpress/datakit-project/issues
Keywords: datakit
Platform: Any
Classifier: Development Status :: 5 - Production/Stable
Classifier: Environment :: Console
Classifier: Intended Audience :: Developers
Classifier: License :: OSI Approved :: ISC License (ISCL)
Classifier: Natural Language :: English
Classifier: Programming Language :: Python :: 3.5
Classifier: Programming Language :: Python :: 3.6
Classifier: Programming Language :: Python :: 3.7
Requires-Dist: click
Requires-Dist: cliff
Requires-Dist: cookiecutter (>=1.6.0)
Requires-Dist: datakit-core
Requires-Dist: prettytable
